{
  "year": 2025,
  "month": "september",
  "working_days": 26,
  "previous_months": [
    "july",
    "august"
  ],
  "file_paths": {
    "basic_manpower": "input_files/basic manpower data september.csv",
    "attendance": "input_files/attendance/original/attendance data september.csv",
    "5prs": "input_files/5prs data september.csv",
    "aql_current": "input_files/AQL history/1.HSRG AQL REPORT-SEPTEMBER.2025.csv",
    "previous_incentive": "output_files/output_QIP_incentive_august_2025_Complete_V9.0_Complete.csv"
  },
  "output_prefix": "output_QIP_incentive_september_2025",
  "working_days_source": "attendance_data",
  "working_days_updated_at": "2025-11-22T11:15:20.463336",
  "data_source": "google_drive",
  "last_updated": "2025-11-22T11:15:20.463353",
  "created_at": "2025-11-22T00:53:11.606735"
}